json4humans/__init__.py
json4humans/cli.py
json4humans/env.py
json4humans/grammar/json.lark
json4humans/grammar/json5.lark
json4humans/grammar/jsonc.lark
json4humans/grammar/wsc.lark
json4humans/json.py
json4humans/json5.py
json4humans/jsonc.py
json4humans/style.py
json4humans/types.py
json4humans/wsc.py
json4humans-0.1.0.dist-info/WHEEL
json4humans-0.1.0.dist-info/METADATA
json4humans-0.1.0.dist-info/license_files/LICENSE
json4humans-0.1.0.dist-info/RECORD
