Metadata-Version: 2.1
Name: json4humans
Version: 0.1.0
Summary: Python tools for JSONC and JSON5 (aka. JSON for humans)
License: MIT
Author-email: Axel H. <noirbizarre@gmail.com>
Requires-Python: >=3.10
Requires-Dist: lark[regex]>=1.1.2
